[
	{
		"key":"mongodb.embedded",
		"value":"false",
		"name":"Embedded MongoDB",
		"description":"Use embedded MongoDB (if no DB is installed)."
	},
	{
		"key":"mongodb.host",
		"value":"localhost",
		"name":"MongoDB host",
		"description":"Host to connect to MongoDB (if not embedded)"
	},
	{
		"key":"mongodb.port",
		"value":"27017",
		"name":"MongoDB port",
		"description":"Port used by MongoDB (standalone and embedded)"
	},
	{
		"key":"mongodb.databaseName",
		"value":"mediamanager-test",
		"name":"Database name",
		"description":"MongoDB database's name."
	},
	{
		"key":"mongodb.embedded.directory",
		"value":"target/mongodb/files",
		"name":"Embedded local file",
		"description":"File where MongoDB stores data (default : ${user.home}/.mediamanager/mongodb)."
	}
]